README.rst
setup.cfg
setup.py
octopush/__init__.py
octopush/ows.py
octopush/sms.py
octopush.egg-info/PKG-INFO
octopush.egg-info/SOURCES.txt
octopush.egg-info/dependency_links.txt
octopush.egg-info/requires.txt
octopush.egg-info/top_level.txt