Metadata-Version: 1.1
Name: octopush
Version: 1.0.0
Summary: Python library for Octopush API
Home-page: https://github.com/bearburger/octopush-api-python
Author: Octopush
Author-email: UNKNOWN
License: MIT
Keywords: octopush sms
Platform: UNKNOWN
Classifier: Development Status :: 5 - Production/Stable
Classifier: Intended Audience :: Developers
Classifier: License :: OSI Approved :: Apache Software License
Classifier: Operating System :: OS Independent
Classifier: Topic :: Software Development :: Libraries :: Python Modules
Classifier: Topic :: Internet
Classifier: Programming Language :: Python
Classifier: Programming Language :: Python :: 2
Classifier: Programming Language :: Python :: 2.7
Classifier: Programming Language :: Python :: 3
Classifier: Programming Language :: Python :: 3.5
